bin/__init__.py
bin/lsb.py
bin/parity.py
bin/red.py
bin/statistics.py
stegano/__init__.py
stegano/exifHeader/__init__.py
stegano/exifHeader/exifHeader.py
stegano/lsb/__init__.py
stegano/lsb/generators.py
stegano/lsb/lsb.py
stegano/red/__init__.py
stegano/red/red.py
stegano/steganalysis/__init__.py
stegano/steganalysis/parity.py
stegano/steganalysis/statistics.py
stegano/tools.py
stegano-1.0.0.dist-info/COPYING
stegano-1.0.0.dist-info/METADATA
stegano-1.0.0.dist-info/WHEEL
stegano-1.0.0.dist-info/entry_points.txt
stegano-1.0.0.dist-info/RECORD
