Metadata-Version: 2.3
Name: stegano
Version: 1.0.0
Summary: A pure Python Steganography module.
License: GPL-3.0-or-later
Keywords: Steganography,Security,Stegano
Author: Cédric Bonhomme
Author-email: cedric@cedricbonhomme.org
Requires-Python: >=3.10,<4.0
Classifier: Development Status :: 5 - Production/Stable
Classifier: Environment :: Console
Classifier: Intended Audience :: Developers
Classifier: Intended Audience :: Science/Research
Classifier: License :: OSI Approved :: GNU General Public License v3 or later (GPLv3+)
Classifier: Operating System :: POSIX :: Linux
Classifier: Programming Language :: Python :: 3
Classifier: Programming Language :: Python :: 3.10
Classifier: Programming Language :: Python :: 3.11
Classifier: Programming Language :: Python :: 3.12
Classifier: Programming Language :: Python :: 3.13
Classifier: Topic :: Security
Requires-Dist: crayons (>=0.4.0)
Requires-Dist: opencv-python (>=4.8.1.78)
Requires-Dist: piexif (>=1.1.3)
Requires-Dist: pillow (>=9.5,<11.0)
Project-URL: Changelog, https://github.com/cedricbonhomme/Stegano/blob/master/CHANGELOG.md
Project-URL: Documentation, https://stegano.readthedocs.io
Project-URL: Homepage, https://github.com/cedricbonhomme/Stegano
Project-URL: Repository, https://github.com/cedricbonhomme/Stegano
